{
  "config": {
    "attention": {
      "block_size": 16,
      "causal": true,
      "degree": 8,
      "graph_artifact": "outputs/copy_v06_graph_search/selected_graph.json",
      "methods": [
        "dense",
        "local",
        "random_regular",
        "zigzag_certified",
        "zigzag_boolean"
      ],
      "multiplicity": {
        "boolean_ablation": true,
        "mode": "unique_log_m"
      },
      "runtime_graph": {
        "B": 16,
        "G_type": "permutation_regular",
        "H_type": "permutation_regular",
        "T": 1040,
        "d": 8,
        "graph_artifact": "outputs/copy_v06_graph_search/selected_graph.json",
        "graph_certified": true,
        "graph_id": "v06_B16_d8_s2_c41f9afbd3840ed1",
        "graph_seed": 2,
        "q": 65
      }
    },
    "model": {
      "architecture": "transformer",
      "attention_backend": "auto_split",
      "d_model": 128,
      "dropout": 0.1,
      "ffn_dim": 256,
      "heads": 4,
      "layers": 8
    },
    "output": {
      "curve_format": "png",
      "plot_curves": true,
      "root": "outputs/copy_v06_main_n512"
    },
    "task": {
      "data": "online",
      "eval_lengths": [
        512
      ],
      "mode": "full_copy",
      "name": "copy",
      "num_values": 4,
      "special_tokens": {
        "eos": 6,
        "pad": 0,
        "sep": 5
      },
      "train_lengths": [
        512
      ]
    },
    "train": {
      "batch_size": 16,
      "checkpoint_every": 500,
      "eval_batches": 50,
      "eval_every": 50,
      "learning_rate": 0.001,
      "log_every": 50,
      "optimizer": "adamw",
      "seeds": [
        0
      ],
      "steps": 5000
    },
    "version": "v06"
  },
  "extra_runs_preserved_not_in_main_table": [
    "train_N512_seed1_dense",
    "train_N512_seed1_local",
    "train_N512_seed1_random_regular",
    "train_N512_seed1_zigzag_boolean",
    "train_N512_seed1_zigzag_certified",
    "train_N512_seed2_dense",
    "train_N512_seed2_local",
    "train_N512_seed2_random_regular",
    "train_N512_seed2_zigzag_boolean",
    "train_N512_seed2_zigzag_certified"
  ],
  "method_results": [
    {
      "N_train": 512,
      "T": 1040,
      "T_raw": 1026,
      "attention_backend": "dense_mask",
      "batch_size": 16,
      "block_pair_shape": null,
      "block_size": 16,
      "degree": 8,
      "device": "cuda",
      "elapsed_sec": 731.5682563651353,
      "evals": [
        {
          "B": 16,
          "CUDA_VISIBLE_DEVICES": "3",
          "G_type": "permutation_regular",
          "H_type": "permutation_regular",
          "N_eval": 512,
          "N_train": 512,
          "T": 1040,
          "T_raw": 1026,
          "architecture": "transformer",
          "artifact_dir": "outputs/copy_v06_main_n512/train_N512_seed0_dense",
          "attention_backend": "dense_mask",
          "attention_pair_count_after_causal": 541320,
          "average_shortest_path": 1.0,
          "batch_size": 16,
          "block_pair_shape": null,
          "causal": true,
          "certified": false,
          "command": "/home/huiwei/miniconda3/envs/ysx_base/bin/python scripts/synthetic_mvp.py --config configs/copy_v06_main_n512.json --output-dir outputs/copy_v06_main_n512",
          "config_path": "configs/copy_v06_main_n512.json",
          "config_sha256": "7e9c686443ac544daa2a3333a1785c9568272415f90c77ab7a0dbbf59a77ed9b",
          "copy_mode": "full_copy",
          "d": 8,
          "d_model": 128,
          "data_mode": "online",
          "dropout": 0.1,
          "duplicate_rate": 0.49951923076923077,
          "effective_K_max_after_causal": 1040,
          "effective_K_mean_after_causal": 520.5,
          "effective_K_min_after_causal": 1,
          "elapsed_sec": 731.5682563651353,
          "eos_token": 6,
          "eval_batches": 50,
          "eval_eos_accuracy": 1.0,
          "eval_every": 50,
          "eval_loss": 4.524973061052151e-05,
          "eval_sequence_accuracy": 0.99875,
          "eval_token_accuracy": 0.9999975633528265,
          "failure_reason": "",
          "ffn_dim": 256,
          "final_train_loss": 0.03959784656763077,
          "git_commit": "525791fb5f020146bbd8aee3400c3ac7fb998521",
          "gpu_name": "NVIDIA A100-SXM4-80GB",
          "graph_certified": "",
          "graph_id": "v06_B16_d8_s2_c41f9afbd3840ed1",
          "graph_seed": 2,
          "heads": 4,
          "host": "hhpc",
          "implementation_certified": "",
          "lambda_G": 0.4430783779678246,
          "layers": 8,
          "learning_rate": 0.001,
          "local_or_remote": "remote",
          "log_every": 50,
          "log_path": "logs/copy_v06_main_n512_20260612_220241.log",
          "method": "dense",
          "metrics_path": "outputs/copy_v06_main_n512/train_N512_seed0_dense/metrics.jsonl",
          "mu_H": 0.5491481939947735,
          "multiplicity_mode": "unique_log_m",
          "neighbor_shape": null,
          "num_values": 4,
          "optimizer": "adamw",
          "output_dir": "outputs/copy_v06_main_n512/train_N512_seed0_dense",
          "pad_token": 0,
          "peak_allocated_gb": 5.898440837860107,
          "peak_reserved_gb": 6.12890625,
          "pre_causal_pair_count": 1081600,
          "pre_causal_unique_K_mean": 1040.0,
          "raw_K": 1040,
          "remote_local_overlap_mean": 0.0,
          "rho_bound": 0.860373989287474,
          "rho_exact": 0.5999831601197602,
          "run_id": "train_N512_seed0_dense",
          "seed": 0,
          "self_loop_rate": 1.0,
          "sep_token": 5,
          "status": "ok",
          "steps": 5000,
          "target_in_1hop_rate": 0.9980506822612085,
          "target_in_2hop_rate": 0.9980506822612085,
          "target_in_Lhop_rate": 0.9980506822612085,
          "task": "copy",
          "theory_aligned_method": false,
          "timestamp": "2026-06-12T14:15:21.540834+00:00",
          "tokens_per_sec": 113728.2806848221,
          "torch_version": "2.10.0+cu128",
          "training_curves_path": "outputs/copy_v06_main_n512/train_N512_seed0_dense/training_curves.png",
          "unique_K_mean": 520.5,
          "unreachable_rate": 0.001949317738791423,
          "version": "v06"
        }
      ],
      "final_train_loss": 0.03959784656763077,
      "final_valid_loss": 4.524973061052151e-05,
      "final_valid_token_accuracy": 0.9999975633528265,
      "gpu_name": "NVIDIA A100-SXM4-80GB",
      "mask": {
        "attention_pair_count": 541320,
        "duplicate_rate": 0.49951923076923077,
        "duplicate_rate_estimate": 0.49951923076923077,
        "effective_k_max": 1040,
        "effective_k_mean": 520.5,
        "effective_k_min": 1,
        "multiplicity_max": 1,
        "multiplicity_mean_nonzero": 1.0,
        "pre_causal_pair_count": 1081600,
        "pre_causal_unique_k_mean": 1040.0,
        "raw_k": 1040,
        "self_loop_rate": 1.0,
        "unique_k_max": 1040,
        "unique_k_mean": 520.5,
        "unique_k_min": 1
      },
      "method": "dense",
      "metrics_path": "outputs/copy_v06_main_n512/train_N512_seed0_dense/metrics.jsonl",
      "neighbor_shape": null,
      "peak_allocated_gb": 5.898440837860107,
      "peak_reserved_gb": 6.12890625,
      "shortcut_diagnostics": [
        {
          "B": 16,
          "N": 512,
          "T": 1040,
          "attention_pair_count": 1081600,
          "average_shortest_path": 1.0,
          "d": 8,
          "layers": 8,
          "mask_scope": "structural",
          "method": "dense",
          "raw_K": 1040,
          "seed": 0,
          "target_in_1hop_rate": 1.0,
          "target_in_2hop_rate": 1.0,
          "target_in_Lhop_rate": 1.0,
          "unreachable_rate": 0.0
        },
        {
          "B": 16,
          "N": 512,
          "T": 1040,
          "attention_pair_count": 541320,
          "average_shortest_path": 1.0,
          "d": 8,
          "layers": 8,
          "mask_scope": "causal_effective",
          "method": "dense",
          "raw_K": 1040,
          "seed": 0,
          "target_in_1hop_rate": 0.9980506822612085,
          "target_in_2hop_rate": 0.9980506822612085,
          "target_in_Lhop_rate": 0.9980506822612085,
          "unreachable_rate": 0.001949317738791423
        }
      ],
      "steps": 5000,
      "task": "copy",
      "task_spec": {
        "eos_token": 6,
        "num_values": 4,
        "pad_token": 0,
        "sep_token": 5
      },
      "tokens_per_sec": 113728.2806848221,
      "training_curves_path": "outputs/copy_v06_main_n512/train_N512_seed0_dense/training_curves.png"
    },
    {
      "N_train": 512,
      "T": 1040,
      "T_raw": 1026,
      "attention_backend": "split",
      "batch_size": 16,
      "block_pair_shape": null,
      "block_size": 16,
      "degree": 8,
      "device": "cuda",
      "elapsed_sec": 261.82906144857407,
      "evals": [
        {
          "B": 16,
          "CUDA_VISIBLE_DEVICES": "3",
          "G_type": "permutation_regular",
          "H_type": "permutation_regular",
          "N_eval": 512,
          "N_train": 512,
          "T": 1040,
          "T_raw": 1026,
          "architecture": "transformer",
          "artifact_dir": "outputs/copy_v06_main_n512/train_N512_seed0_local",
          "attention_backend": "split",
          "attention_pair_count_after_causal": 8840,
          "average_shortest_path": Infinity,
          "batch_size": 16,
          "block_pair_shape": null,
          "causal": true,
          "certified": false,
          "command": "/home/huiwei/miniconda3/envs/ysx_base/bin/python scripts/synthetic_mvp.py --config configs/copy_v06_main_n512.json --output-dir outputs/copy_v06_main_n512",
          "config_path": "configs/copy_v06_main_n512.json",
          "config_sha256": "7e9c686443ac544daa2a3333a1785c9568272415f90c77ab7a0dbbf59a77ed9b",
          "copy_mode": "full_copy",
          "d": 8,
          "d_model": 128,
          "data_mode": "online",
          "dropout": 0.1,
          "duplicate_rate": 0.46875,
          "effective_K_max_after_causal": 16,
          "effective_K_mean_after_causal": 8.5,
          "effective_K_min_after_causal": 1,
          "elapsed_sec": 261.82906144857407,
          "eos_token": 6,
          "eval_batches": 50,
          "eval_eos_accuracy": 1.0,
          "eval_every": 50,
          "eval_loss": 1.3836686301231385,
          "eval_sequence_accuracy": 0.0,
          "eval_token_accuracy": 0.25192007797270954,
          "failure_reason": "",
          "ffn_dim": 256,
          "final_train_loss": 1.3837090730667114,
          "git_commit": "525791fb5f020146bbd8aee3400c3ac7fb998521",
          "gpu_name": "NVIDIA A100-SXM4-80GB",
          "graph_certified": "",
          "graph_id": "v06_B16_d8_s2_c41f9afbd3840ed1",
          "graph_seed": 2,
          "heads": 4,
          "host": "hhpc",
          "implementation_certified": "",
          "lambda_G": 0.4430783779678246,
          "layers": 8,
          "learning_rate": 0.001,
          "local_or_remote": "remote",
          "log_every": 50,
          "log_path": "logs/copy_v06_main_n512_20260612_220241.log",
          "method": "local",
          "metrics_path": "outputs/copy_v06_main_n512/train_N512_seed0_local/metrics.jsonl",
          "mu_H": 0.5491481939947735,
          "multiplicity_mode": "unique_log_m",
          "neighbor_shape": [
            1040,
            0
          ],
          "num_values": 4,
          "optimizer": "adamw",
          "output_dir": "outputs/copy_v06_main_n512/train_N512_seed0_local",
          "pad_token": 0,
          "peak_allocated_gb": 0.965355396270752,
          "peak_reserved_gb": 1.138671875,
          "pre_causal_pair_count": 16640,
          "pre_causal_unique_K_mean": 16.0,
          "raw_K": 16,
          "remote_local_overlap_mean": 0.0,
          "rho_bound": 0.860373989287474,
          "rho_exact": 0.5999831601197602,
          "run_id": "train_N512_seed0_local",
          "seed": 0,
          "self_loop_rate": 1.0,
          "sep_token": 5,
          "status": "ok",
          "steps": 5000,
          "target_in_1hop_rate": 0.0,
          "target_in_2hop_rate": 0.0,
          "target_in_Lhop_rate": 0.0,
          "task": "copy",
          "theory_aligned_method": false,
          "timestamp": "2026-06-12T14:19:44.952759+00:00",
          "tokens_per_sec": 317764.5733429837,
          "torch_version": "2.10.0+cu128",
          "training_curves_path": "outputs/copy_v06_main_n512/train_N512_seed0_local/training_curves.png",
          "unique_K_mean": 8.5,
          "unreachable_rate": 1.0,
          "version": "v06"
        }
      ],
      "final_train_loss": 1.3837090730667114,
      "final_valid_loss": 1.3836686301231385,
      "final_valid_token_accuracy": 0.25192007797270954,
      "gpu_name": "NVIDIA A100-SXM4-80GB",
      "mask": {
        "attention_pair_count": 8840,
        "duplicate_rate": 0.46875,
        "duplicate_rate_estimate": 0.46875,
        "effective_k_max": 16,
        "effective_k_mean": 8.5,
        "effective_k_min": 1,
        "multiplicity_max": 1,
        "multiplicity_mean_nonzero": 1.0,
        "pre_causal_pair_count": 16640,
        "pre_causal_unique_k_mean": 16.0,
        "raw_k": 16,
        "self_loop_rate": 1.0,
        "unique_k_max": 16,
        "unique_k_mean": 8.5,
        "unique_k_min": 1
      },
      "method": "local",
      "metrics_path": "outputs/copy_v06_main_n512/train_N512_seed0_local/metrics.jsonl",
      "neighbor_shape": [
        1040,
        0
      ],
      "peak_allocated_gb": 0.965355396270752,
      "peak_reserved_gb": 1.138671875,
      "shortcut_diagnostics": [
        {
          "B": 16,
          "N": 512,
          "T": 1040,
          "attention_pair_count": 16640,
          "average_shortest_path": 1.0,
          "d": 8,
          "layers": 8,
          "mask_scope": "structural",
          "method": "local",
          "raw_K": 16,
          "seed": 0,
          "target_in_1hop_rate": 0.001949317738791423,
          "target_in_2hop_rate": 0.001949317738791423,
          "target_in_Lhop_rate": 0.001949317738791423,
          "unreachable_rate": 0.9980506822612085
        },
        {
          "B": 16,
          "N": 512,
          "T": 1040,
          "attention_pair_count": 8840,
          "average_shortest_path": Infinity,
          "d": 8,
          "layers": 8,
          "mask_scope": "causal_effective",
          "method": "local",
          "raw_K": 16,
          "seed": 0,
          "target_in_1hop_rate": 0.0,
          "target_in_2hop_rate": 0.0,
          "target_in_Lhop_rate": 0.0,
          "unreachable_rate": 1.0
        }
      ],
      "steps": 5000,
      "task": "copy",
      "task_spec": {
        "eos_token": 6,
        "num_values": 4,
        "pad_token": 0,
        "sep_token": 5
      },
      "tokens_per_sec": 317764.5733429837,
      "training_curves_path": "outputs/copy_v06_main_n512/train_N512_seed0_local/training_curves.png"
    },
    {
      "N_train": 512,
      "T": 1040,
      "T_raw": 1026,
      "attention_backend": "split",
      "batch_size": 16,
      "block_pair_shape": null,
      "block_size": 16,
      "degree": 8,
      "device": "cuda",
      "elapsed_sec": 2242.2606650125235,
      "evals": [
        {
          "B": 16,
          "CUDA_VISIBLE_DEVICES": "3",
          "G_type": "permutation_regular",
          "H_type": "permutation_regular",
          "N_eval": 512,
          "N_train": 512,
          "T": 1040,
          "T_raw": 1026,
          "architecture": "transformer",
          "artifact_dir": "outputs/copy_v06_main_n512/train_N512_seed0_random_regular",
          "attention_backend": "split",
          "attention_pair_count_after_causal": 41691,
          "average_shortest_path": 2.00390625,
          "batch_size": 16,
          "block_pair_shape": null,
          "causal": true,
          "certified": false,
          "command": "/home/huiwei/miniconda3/envs/ysx_base/bin/python scripts/synthetic_mvp.py --config configs/copy_v06_main_n512.json --output-dir outputs/copy_v06_main_n512",
          "config_path": "configs/copy_v06_main_n512.json",
          "config_sha256": "7e9c686443ac544daa2a3333a1785c9568272415f90c77ab7a0dbbf59a77ed9b",
          "copy_mode": "full_copy",
          "d": 8,
          "d_model": 128,
          "data_mode": "online",
          "dropout": 0.1,
          "duplicate_rate": 0.49890623092651365,
          "effective_K_max_after_causal": 79,
          "effective_K_mean_after_causal": 40.087501525878906,
          "effective_K_min_after_causal": 1,
          "elapsed_sec": 2242.2606650125235,
          "eos_token": 6,
          "eval_batches": 50,
          "eval_eos_accuracy": 1.0,
          "eval_every": 50,
          "eval_loss": 0.22453420966863633,
          "eval_sequence_accuracy": 0.0,
          "eval_token_accuracy": 0.8785794346978557,
          "failure_reason": "",
          "ffn_dim": 256,
          "final_train_loss": 0.24009886384010315,
          "git_commit": "525791fb5f020146bbd8aee3400c3ac7fb998521",
          "gpu_name": "NVIDIA A100-SXM4-80GB",
          "graph_certified": "",
          "graph_id": "v06_B16_d8_s2_c41f9afbd3840ed1",
          "graph_seed": 2,
          "heads": 4,
          "host": "hhpc",
          "implementation_certified": false,
          "lambda_G": 0.4430783779678246,
          "layers": 8,
          "learning_rate": 0.001,
          "local_or_remote": "remote",
          "log_every": 50,
          "log_path": "logs/copy_v06_main_n512_20260612_220241.log",
          "method": "random_regular",
          "metrics_path": "outputs/copy_v06_main_n512/train_N512_seed0_random_regular/metrics.jsonl",
          "mu_H": 0.5491481939947735,
          "multiplicity_mode": "unique_log_m",
          "neighbor_shape": [
            1040,
            64
          ],
          "num_values": 4,
          "optimizer": "adamw",
          "output_dir": "outputs/copy_v06_main_n512/train_N512_seed0_random_regular",
          "pad_token": 0,
          "peak_allocated_gb": 10.50410270690918,
          "peak_reserved_gb": 10.986328125,
          "pre_causal_pair_count": 81179,
          "pre_causal_unique_K_mean": 78.05673076923077,
          "raw_K": 80,
          "remote_local_overlap_mean": 0.0,
          "rho_bound": 0.860373989287474,
          "rho_exact": 0.5999831601197602,
          "run_id": "train_N512_seed0_random_regular",
          "seed": 0,
          "self_loop_rate": 1.0,
          "sep_token": 5,
          "status": "ok",
          "steps": 5000,
          "target_in_1hop_rate": 0.042884990253411304,
          "target_in_2hop_rate": 0.9512670565302144,
          "target_in_Lhop_rate": 0.9980506822612085,
          "task": "copy",
          "theory_aligned_method": false,
          "timestamp": "2026-06-12T14:57:15.782179+00:00",
          "tokens_per_sec": 37105.40941926362,
          "torch_version": "2.10.0+cu128",
          "training_curves_path": "outputs/copy_v06_main_n512/train_N512_seed0_random_regular/training_curves.png",
          "unique_K_mean": 40.087501525878906,
          "unreachable_rate": 0.001949317738791423,
          "version": "v06"
        }
      ],
      "final_train_loss": 0.24009886384010315,
      "final_valid_loss": 0.22453420966863633,
      "final_valid_token_accuracy": 0.8785794346978557,
      "gpu_name": "NVIDIA A100-SXM4-80GB",
      "mask": {
        "attention_pair_count": 41691,
        "duplicate_rate": 0.49890623092651365,
        "duplicate_rate_estimate": 0.49890623092651365,
        "effective_k_max": 79,
        "effective_k_mean": 40.087501525878906,
        "effective_k_min": 1,
        "multiplicity_max": 3,
        "multiplicity_mean_nonzero": 1.0248956010790968,
        "pre_causal_pair_count": 81179,
        "pre_causal_unique_k_mean": 78.05673076923077,
        "raw_k": 80,
        "self_loop_rate": 1.0,
        "unique_k_max": 79,
        "unique_k_mean": 40.087501525878906,
        "unique_k_min": 1
      },
      "method": "random_regular",
      "metrics_path": "outputs/copy_v06_main_n512/train_N512_seed0_random_regular/metrics.jsonl",
      "neighbor_shape": [
        1040,
        64
      ],
      "peak_allocated_gb": 10.50410270690918,
      "peak_reserved_gb": 10.986328125,
      "shortcut_diagnostics": [
        {
          "B": 16,
          "N": 512,
          "T": 1040,
          "attention_pair_count": 81179,
          "average_shortest_path": 1.95906432748538,
          "d": 8,
          "layers": 8,
          "mask_scope": "structural",
          "method": "random_regular",
          "raw_K": 80,
          "seed": 0,
          "target_in_1hop_rate": 0.04483430799220273,
          "target_in_2hop_rate": 0.9961013645224172,
          "target_in_Lhop_rate": 1.0,
          "unreachable_rate": 0.0
        },
        {
          "B": 16,
          "N": 512,
          "T": 1040,
          "attention_pair_count": 41691,
          "average_shortest_path": 2.00390625,
          "d": 8,
          "layers": 8,
          "mask_scope": "causal_effective",
          "method": "random_regular",
          "raw_K": 80,
          "seed": 0,
          "target_in_1hop_rate": 0.042884990253411304,
          "target_in_2hop_rate": 0.9512670565302144,
          "target_in_Lhop_rate": 0.9980506822612085,
          "unreachable_rate": 0.001949317738791423
        }
      ],
      "steps": 5000,
      "task": "copy",
      "task_spec": {
        "eos_token": 6,
        "num_values": 4,
        "pad_token": 0,
        "sep_token": 5
      },
      "tokens_per_sec": 37105.40941926362,
      "training_curves_path": "outputs/copy_v06_main_n512/train_N512_seed0_random_regular/training_curves.png"
    },
    {
      "N_train": 512,
      "T": 1040,
      "T_raw": 1026,
      "attention_backend": "split",
      "batch_size": 16,
      "block_pair_shape": null,
      "block_size": 16,
      "degree": 8,
      "device": "cuda",
      "elapsed_sec": 1866.2317732032388,
      "evals": [
        {
          "B": 16,
          "CUDA_VISIBLE_DEVICES": "3",
          "G_type": "permutation_regular",
          "H_type": "permutation_regular",
          "N_eval": 512,
          "N_train": 512,
          "T": 1040,
          "T_raw": 1026,
          "architecture": "transformer",
          "artifact_dir": "outputs/copy_v06_main_n512/train_N512_seed0_zigzag_boolean",
          "attention_backend": "split",
          "attention_pair_count_after_causal": 31033,
          "average_shortest_path": 2.733201581027668,
          "batch_size": 16,
          "block_pair_shape": null,
          "causal": true,
          "certified": false,
          "command": "/home/huiwei/miniconda3/envs/ysx_base/bin/python scripts/synthetic_mvp.py --config configs/copy_v06_main_n512.json --output-dir outputs/copy_v06_main_n512",
          "config_path": "configs/copy_v06_main_n512.json",
          "config_sha256": "7e9c686443ac544daa2a3333a1785c9568272415f90c77ab7a0dbbf59a77ed9b",
          "copy_mode": "full_copy",
          "d": 8,
          "d_model": 128,
          "data_mode": "online",
          "dropout": 0.1,
          "duplicate_rate": 0.6270072221755981,
          "effective_K_max_after_causal": 63,
          "effective_K_mean_after_causal": 29.83942222595215,
          "effective_K_min_after_causal": 1,
          "elapsed_sec": 1866.2317732032388,
          "eos_token": 6,
          "eval_batches": 50,
          "eval_eos_accuracy": 1.0,
          "eval_every": 50,
          "eval_loss": 0.6918463325500488,
          "eval_sequence_accuracy": 0.0,
          "eval_token_accuracy": 0.6280433723196881,
          "failure_reason": "",
          "ffn_dim": 256,
          "final_train_loss": 0.6976962089538574,
          "git_commit": "525791fb5f020146bbd8aee3400c3ac7fb998521",
          "gpu_name": "NVIDIA A100-SXM4-80GB",
          "graph_certified": true,
          "graph_id": "v06_B16_d8_s2_c41f9afbd3840ed1",
          "graph_seed": 2,
          "heads": 4,
          "host": "hhpc",
          "implementation_certified": false,
          "lambda_G": 0.4430783779678246,
          "layers": 8,
          "learning_rate": 0.001,
          "local_or_remote": "remote",
          "log_every": 50,
          "log_path": "logs/copy_v06_main_n512_20260612_220241.log",
          "method": "zigzag_boolean",
          "metrics_path": "outputs/copy_v06_main_n512/train_N512_seed0_zigzag_boolean/metrics.jsonl",
          "mu_H": 0.5491481939947735,
          "multiplicity_mode": "unique_log_m",
          "neighbor_shape": [
            1040,
            53
          ],
          "num_values": 4,
          "optimizer": "adamw",
          "output_dir": "outputs/copy_v06_main_n512/train_N512_seed0_zigzag_boolean",
          "pad_token": 0,
          "peak_allocated_gb": 8.886736392974854,
          "peak_reserved_gb": 9.1640625,
          "pre_causal_pair_count": 61230,
          "pre_causal_unique_K_mean": 58.875,
          "raw_K": 80,
          "remote_local_overlap_mean": 0.0,
          "rho_bound": 0.860373989287474,
          "rho_exact": 0.5999831601197602,
          "run_id": "train_N512_seed0_zigzag_boolean",
          "seed": 0,
          "self_loop_rate": 1.0,
          "sep_token": 5,
          "status": "ok",
          "steps": 5000,
          "target_in_1hop_rate": 0.04483430799220273,
          "target_in_2hop_rate": 0.39571150097465885,
          "target_in_Lhop_rate": 0.98635477582846,
          "task": "copy",
          "theory_aligned_method": false,
          "timestamp": "2026-06-12T16:01:02.517166+00:00",
          "tokens_per_sec": 44581.815182148464,
          "torch_version": "2.10.0+cu128",
          "training_curves_path": "outputs/copy_v06_main_n512/train_N512_seed0_zigzag_boolean/training_curves.png",
          "unique_K_mean": 29.83942222595215,
          "unreachable_rate": 0.01364522417153996,
          "version": "v06"
        }
      ],
      "final_train_loss": 0.6976962089538574,
      "final_valid_loss": 0.6918463325500488,
      "final_valid_token_accuracy": 0.6280433723196881,
      "gpu_name": "NVIDIA A100-SXM4-80GB",
      "mask": {
        "attention_pair_count": 31033,
        "duplicate_rate": 0.6270072221755981,
        "duplicate_rate_estimate": 0.6270072221755981,
        "effective_k_max": 63,
        "effective_k_mean": 29.83942222595215,
        "effective_k_min": 1,
        "multiplicity_max": 1,
        "multiplicity_mean_nonzero": 1.0,
        "pre_causal_pair_count": 61230,
        "pre_causal_unique_k_mean": 58.875,
        "raw_k": 80,
        "self_loop_rate": 1.0,
        "unique_k_max": 63,
        "unique_k_mean": 29.83942222595215,
        "unique_k_min": 1
      },
      "method": "zigzag_boolean",
      "metrics_path": "outputs/copy_v06_main_n512/train_N512_seed0_zigzag_boolean/metrics.jsonl",
      "neighbor_shape": [
        1040,
        53
      ],
      "peak_allocated_gb": 8.886736392974854,
      "peak_reserved_gb": 9.1640625,
      "shortcut_diagnostics": [
        {
          "B": 16,
          "N": 512,
          "T": 1040,
          "attention_pair_count": 61230,
          "average_shortest_path": 2.358674463937622,
          "d": 8,
          "layers": 8,
          "mask_scope": "structural",
          "method": "zigzag_boolean",
          "raw_K": 80,
          "seed": 0,
          "target_in_1hop_rate": 0.04678362573099415,
          "target_in_2hop_rate": 0.594541910331384,
          "target_in_Lhop_rate": 1.0,
          "unreachable_rate": 0.0
        },
        {
          "B": 16,
          "N": 512,
          "T": 1040,
          "attention_pair_count": 31033,
          "average_shortest_path": 2.733201581027668,
          "d": 8,
          "layers": 8,
          "mask_scope": "causal_effective",
          "method": "zigzag_boolean",
          "raw_K": 80,
          "seed": 0,
          "target_in_1hop_rate": 0.04483430799220273,
          "target_in_2hop_rate": 0.39571150097465885,
          "target_in_Lhop_rate": 0.98635477582846,
          "unreachable_rate": 0.01364522417153996
        }
      ],
      "steps": 5000,
      "task": "copy",
      "task_spec": {
        "eos_token": 6,
        "num_values": 4,
        "pad_token": 0,
        "sep_token": 5
      },
      "tokens_per_sec": 44581.815182148464,
      "training_curves_path": "outputs/copy_v06_main_n512/train_N512_seed0_zigzag_boolean/training_curves.png"
    },
    {
      "N_train": 512,
      "T": 1040,
      "T_raw": 1026,
      "attention_backend": "split",
      "batch_size": 16,
      "block_pair_shape": null,
      "block_size": 16,
      "degree": 8,
      "device": "cuda",
      "elapsed_sec": 1949.7408073116094,
      "evals": [
        {
          "B": 16,
          "CUDA_VISIBLE_DEVICES": "3",
          "G_type": "permutation_regular",
          "H_type": "permutation_regular",
          "N_eval": 512,
          "N_train": 512,
          "T": 1040,
          "T_raw": 1026,
          "architecture": "transformer",
          "artifact_dir": "outputs/copy_v06_main_n512/train_N512_seed0_zigzag_certified",
          "attention_backend": "split",
          "attention_pair_count_after_causal": 31033,
          "average_shortest_path": 2.733201581027668,
          "batch_size": 16,
          "block_pair_shape": null,
          "causal": true,
          "certified": true,
          "command": "/home/huiwei/miniconda3/envs/ysx_base/bin/python scripts/synthetic_mvp.py --config configs/copy_v06_main_n512.json --output-dir outputs/copy_v06_main_n512",
          "config_path": "configs/copy_v06_main_n512.json",
          "config_sha256": "7e9c686443ac544daa2a3333a1785c9568272415f90c77ab7a0dbbf59a77ed9b",
          "copy_mode": "full_copy",
          "d": 8,
          "d_model": 128,
          "data_mode": "online",
          "dropout": 0.1,
          "duplicate_rate": 0.6270072221755981,
          "effective_K_max_after_causal": 63,
          "effective_K_mean_after_causal": 29.83942222595215,
          "effective_K_min_after_causal": 1,
          "elapsed_sec": 1949.7408073116094,
          "eos_token": 6,
          "eval_batches": 50,
          "eval_eos_accuracy": 1.0,
          "eval_every": 50,
          "eval_loss": 0.6976403307914734,
          "eval_sequence_accuracy": 0.0,
          "eval_token_accuracy": 0.6248513645224172,
          "failure_reason": "",
          "ffn_dim": 256,
          "final_train_loss": 0.7057569622993469,
          "git_commit": "525791fb5f020146bbd8aee3400c3ac7fb998521",
          "gpu_name": "NVIDIA A100-SXM4-80GB",
          "graph_certified": true,
          "graph_id": "v06_B16_d8_s2_c41f9afbd3840ed1",
          "graph_seed": 2,
          "heads": 4,
          "host": "hhpc",
          "implementation_certified": true,
          "lambda_G": 0.4430783779678246,
          "layers": 8,
          "learning_rate": 0.001,
          "local_or_remote": "remote",
          "log_every": 50,
          "log_path": "logs/copy_v06_main_n512_20260612_220241.log",
          "method": "zigzag_certified",
          "metrics_path": "outputs/copy_v06_main_n512/train_N512_seed0_zigzag_certified/metrics.jsonl",
          "mu_H": 0.5491481939947735,
          "multiplicity_mode": "unique_log_m",
          "neighbor_shape": [
            1040,
            53
          ],
          "num_values": 4,
          "optimizer": "adamw",
          "output_dir": "outputs/copy_v06_main_n512/train_N512_seed0_zigzag_certified",
          "pad_token": 0,
          "peak_allocated_gb": 8.886380195617676,
          "peak_reserved_gb": 9.1640625,
          "pre_causal_pair_count": 61230,
          "pre_causal_unique_K_mean": 58.875,
          "raw_K": 80,
          "remote_local_overlap_mean": 0.0,
          "rho_bound": 0.860373989287474,
          "rho_exact": 0.5999831601197602,
          "run_id": "train_N512_seed0_zigzag_certified",
          "seed": 0,
          "self_loop_rate": 1.0,
          "sep_token": 5,
          "status": "ok",
          "steps": 5000,
          "target_in_1hop_rate": 0.04483430799220273,
          "target_in_2hop_rate": 0.39571150097465885,
          "target_in_Lhop_rate": 0.98635477582846,
          "task": "copy",
          "theory_aligned_method": true,
          "timestamp": "2026-06-12T15:29:50.955522+00:00",
          "tokens_per_sec": 42672.33864521711,
          "torch_version": "2.10.0+cu128",
          "training_curves_path": "outputs/copy_v06_main_n512/train_N512_seed0_zigzag_certified/training_curves.png",
          "unique_K_mean": 29.83942222595215,
          "unreachable_rate": 0.01364522417153996,
          "version": "v06"
        }
      ],
      "final_train_loss": 0.7057569622993469,
      "final_valid_loss": 0.6976403307914734,
      "final_valid_token_accuracy": 0.6248513645224172,
      "gpu_name": "NVIDIA A100-SXM4-80GB",
      "mask": {
        "attention_pair_count": 31033,
        "duplicate_rate": 0.6270072221755981,
        "duplicate_rate_estimate": 0.6270072221755981,
        "effective_k_max": 63,
        "effective_k_mean": 29.83942222595215,
        "effective_k_min": 1,
        "multiplicity_max": 6,
        "multiplicity_mean_nonzero": 1.3588110403397027,
        "pre_causal_pair_count": 61230,
        "pre_causal_unique_k_mean": 58.875,
        "raw_k": 80,
        "self_loop_rate": 1.0,
        "unique_k_max": 63,
        "unique_k_mean": 29.83942222595215,
        "unique_k_min": 1
      },
      "method": "zigzag_certified",
      "metrics_path": "outputs/copy_v06_main_n512/train_N512_seed0_zigzag_certified/metrics.jsonl",
      "neighbor_shape": [
        1040,
        53
      ],
      "peak_allocated_gb": 8.886380195617676,
      "peak_reserved_gb": 9.1640625,
      "shortcut_diagnostics": [
        {
          "B": 16,
          "N": 512,
          "T": 1040,
          "attention_pair_count": 61230,
          "average_shortest_path": 2.358674463937622,
          "d": 8,
          "layers": 8,
          "mask_scope": "structural",
          "method": "zigzag_certified",
          "raw_K": 80,
          "seed": 0,
          "target_in_1hop_rate": 0.04678362573099415,
          "target_in_2hop_rate": 0.594541910331384,
          "target_in_Lhop_rate": 1.0,
          "unreachable_rate": 0.0
        },
        {
          "B": 16,
          "N": 512,
          "T": 1040,
          "attention_pair_count": 31033,
          "average_shortest_path": 2.733201581027668,
          "d": 8,
          "layers": 8,
          "mask_scope": "causal_effective",
          "method": "zigzag_certified",
          "raw_K": 80,
          "seed": 0,
          "target_in_1hop_rate": 0.04483430799220273,
          "target_in_2hop_rate": 0.39571150097465885,
          "target_in_Lhop_rate": 0.98635477582846,
          "unreachable_rate": 0.01364522417153996
        }
      ],
      "steps": 5000,
      "task": "copy",
      "task_spec": {
        "eos_token": 6,
        "num_values": 4,
        "pad_token": 0,
        "sep_token": 5
      },
      "tokens_per_sec": 42672.33864521711,
      "training_curves_path": "outputs/copy_v06_main_n512/train_N512_seed0_zigzag_certified/training_curves.png"
    }
  ],
  "raw_config_snapshot_path": "outputs/copy_v06_main_n512/raw_config_snapshot.json",
  "repair_notes": [
    "shortcut diagnostics recomputed with within-L-hop semantics",
    "root main result table restricted to configured v06 main seeds",
    "certified is a backward-compatible alias for theory_aligned_method"
  ],
  "results": [
    {
      "B": 16,
      "CUDA_VISIBLE_DEVICES": "3",
      "G_type": "permutation_regular",
      "H_type": "permutation_regular",
      "N_eval": 512,
      "N_train": 512,
      "T": 1040,
      "T_raw": 1026,
      "architecture": "transformer",
      "artifact_dir": "outputs/copy_v06_main_n512/train_N512_seed0_dense",
      "attention_backend": "dense_mask",
      "attention_pair_count_after_causal": 541320,
      "average_shortest_path": 1.0,
      "batch_size": 16,
      "block_pair_shape": null,
      "causal": true,
      "certified": false,
      "command": "/home/huiwei/miniconda3/envs/ysx_base/bin/python scripts/synthetic_mvp.py --config configs/copy_v06_main_n512.json --output-dir outputs/copy_v06_main_n512",
      "config_path": "configs/copy_v06_main_n512.json",
      "config_sha256": "7e9c686443ac544daa2a3333a1785c9568272415f90c77ab7a0dbbf59a77ed9b",
      "copy_mode": "full_copy",
      "d": 8,
      "d_model": 128,
      "data_mode": "online",
      "dropout": 0.1,
      "duplicate_rate": 0.49951923076923077,
      "effective_K_max_after_causal": 1040,
      "effective_K_mean_after_causal": 520.5,
      "effective_K_min_after_causal": 1,
      "elapsed_sec": 731.5682563651353,
      "eos_token": 6,
      "eval_batches": 50,
      "eval_eos_accuracy": 1.0,
      "eval_every": 50,
      "eval_loss": 4.524973061052151e-05,
      "eval_sequence_accuracy": 0.99875,
      "eval_token_accuracy": 0.9999975633528265,
      "failure_reason": "",
      "ffn_dim": 256,
      "final_train_loss": 0.03959784656763077,
      "git_commit": "525791fb5f020146bbd8aee3400c3ac7fb998521",
      "gpu_name": "NVIDIA A100-SXM4-80GB",
      "graph_certified": "",
      "graph_id": "v06_B16_d8_s2_c41f9afbd3840ed1",
      "graph_seed": 2,
      "heads": 4,
      "host": "hhpc",
      "implementation_certified": "",
      "lambda_G": 0.4430783779678246,
      "layers": 8,
      "learning_rate": 0.001,
      "local_or_remote": "remote",
      "log_every": 50,
      "log_path": "logs/copy_v06_main_n512_20260612_220241.log",
      "method": "dense",
      "metrics_path": "outputs/copy_v06_main_n512/train_N512_seed0_dense/metrics.jsonl",
      "mu_H": 0.5491481939947735,
      "multiplicity_mode": "unique_log_m",
      "neighbor_shape": null,
      "num_values": 4,
      "optimizer": "adamw",
      "output_dir": "outputs/copy_v06_main_n512/train_N512_seed0_dense",
      "pad_token": 0,
      "peak_allocated_gb": 5.898440837860107,
      "peak_reserved_gb": 6.12890625,
      "pre_causal_pair_count": 1081600,
      "pre_causal_unique_K_mean": 1040.0,
      "raw_K": 1040,
      "remote_local_overlap_mean": 0.0,
      "rho_bound": 0.860373989287474,
      "rho_exact": 0.5999831601197602,
      "run_id": "train_N512_seed0_dense",
      "seed": 0,
      "self_loop_rate": 1.0,
      "sep_token": 5,
      "status": "ok",
      "steps": 5000,
      "target_in_1hop_rate": 0.9980506822612085,
      "target_in_2hop_rate": 0.9980506822612085,
      "target_in_Lhop_rate": 0.9980506822612085,
      "task": "copy",
      "theory_aligned_method": false,
      "timestamp": "2026-06-12T14:15:21.540834+00:00",
      "tokens_per_sec": 113728.2806848221,
      "torch_version": "2.10.0+cu128",
      "training_curves_path": "outputs/copy_v06_main_n512/train_N512_seed0_dense/training_curves.png",
      "unique_K_mean": 520.5,
      "unreachable_rate": 0.001949317738791423,
      "version": "v06"
    },
    {
      "B": 16,
      "CUDA_VISIBLE_DEVICES": "3",
      "G_type": "permutation_regular",
      "H_type": "permutation_regular",
      "N_eval": 512,
      "N_train": 512,
      "T": 1040,
      "T_raw": 1026,
      "architecture": "transformer",
      "artifact_dir": "outputs/copy_v06_main_n512/train_N512_seed0_local",
      "attention_backend": "split",
      "attention_pair_count_after_causal": 8840,
      "average_shortest_path": Infinity,
      "batch_size": 16,
      "block_pair_shape": null,
      "causal": true,
      "certified": false,
      "command": "/home/huiwei/miniconda3/envs/ysx_base/bin/python scripts/synthetic_mvp.py --config configs/copy_v06_main_n512.json --output-dir outputs/copy_v06_main_n512",
      "config_path": "configs/copy_v06_main_n512.json",
      "config_sha256": "7e9c686443ac544daa2a3333a1785c9568272415f90c77ab7a0dbbf59a77ed9b",
      "copy_mode": "full_copy",
      "d": 8,
      "d_model": 128,
      "data_mode": "online",
      "dropout": 0.1,
      "duplicate_rate": 0.46875,
      "effective_K_max_after_causal": 16,
      "effective_K_mean_after_causal": 8.5,
      "effective_K_min_after_causal": 1,
      "elapsed_sec": 261.82906144857407,
      "eos_token": 6,
      "eval_batches": 50,
      "eval_eos_accuracy": 1.0,
      "eval_every": 50,
      "eval_loss": 1.3836686301231385,
      "eval_sequence_accuracy": 0.0,
      "eval_token_accuracy": 0.25192007797270954,
      "failure_reason": "",
      "ffn_dim": 256,
      "final_train_loss": 1.3837090730667114,
      "git_commit": "525791fb5f020146bbd8aee3400c3ac7fb998521",
      "gpu_name": "NVIDIA A100-SXM4-80GB",
      "graph_certified": "",
      "graph_id": "v06_B16_d8_s2_c41f9afbd3840ed1",
      "graph_seed": 2,
      "heads": 4,
      "host": "hhpc",
      "implementation_certified": "",
      "lambda_G": 0.4430783779678246,
      "layers": 8,
      "learning_rate": 0.001,
      "local_or_remote": "remote",
      "log_every": 50,
      "log_path": "logs/copy_v06_main_n512_20260612_220241.log",
      "method": "local",
      "metrics_path": "outputs/copy_v06_main_n512/train_N512_seed0_local/metrics.jsonl",
      "mu_H": 0.5491481939947735,
      "multiplicity_mode": "unique_log_m",
      "neighbor_shape": [
        1040,
        0
      ],
      "num_values": 4,
      "optimizer": "adamw",
      "output_dir": "outputs/copy_v06_main_n512/train_N512_seed0_local",
      "pad_token": 0,
      "peak_allocated_gb": 0.965355396270752,
      "peak_reserved_gb": 1.138671875,
      "pre_causal_pair_count": 16640,
      "pre_causal_unique_K_mean": 16.0,
      "raw_K": 16,
      "remote_local_overlap_mean": 0.0,
      "rho_bound": 0.860373989287474,
      "rho_exact": 0.5999831601197602,
      "run_id": "train_N512_seed0_local",
      "seed": 0,
      "self_loop_rate": 1.0,
      "sep_token": 5,
      "status": "ok",
      "steps": 5000,
      "target_in_1hop_rate": 0.0,
      "target_in_2hop_rate": 0.0,
      "target_in_Lhop_rate": 0.0,
      "task": "copy",
      "theory_aligned_method": false,
      "timestamp": "2026-06-12T14:19:44.952759+00:00",
      "tokens_per_sec": 317764.5733429837,
      "torch_version": "2.10.0+cu128",
      "training_curves_path": "outputs/copy_v06_main_n512/train_N512_seed0_local/training_curves.png",
      "unique_K_mean": 8.5,
      "unreachable_rate": 1.0,
      "version": "v06"
    },
    {
      "B": 16,
      "CUDA_VISIBLE_DEVICES": "3",
      "G_type": "permutation_regular",
      "H_type": "permutation_regular",
      "N_eval": 512,
      "N_train": 512,
      "T": 1040,
      "T_raw": 1026,
      "architecture": "transformer",
      "artifact_dir": "outputs/copy_v06_main_n512/train_N512_seed0_random_regular",
      "attention_backend": "split",
      "attention_pair_count_after_causal": 41691,
      "average_shortest_path": 2.00390625,
      "batch_size": 16,
      "block_pair_shape": null,
      "causal": true,
      "certified": false,
      "command": "/home/huiwei/miniconda3/envs/ysx_base/bin/python scripts/synthetic_mvp.py --config configs/copy_v06_main_n512.json --output-dir outputs/copy_v06_main_n512",
      "config_path": "configs/copy_v06_main_n512.json",
      "config_sha256": "7e9c686443ac544daa2a3333a1785c9568272415f90c77ab7a0dbbf59a77ed9b",
      "copy_mode": "full_copy",
      "d": 8,
      "d_model": 128,
      "data_mode": "online",
      "dropout": 0.1,
      "duplicate_rate": 0.49890623092651365,
      "effective_K_max_after_causal": 79,
      "effective_K_mean_after_causal": 40.087501525878906,
      "effective_K_min_after_causal": 1,
      "elapsed_sec": 2242.2606650125235,
      "eos_token": 6,
      "eval_batches": 50,
      "eval_eos_accuracy": 1.0,
      "eval_every": 50,
      "eval_loss": 0.22453420966863633,
      "eval_sequence_accuracy": 0.0,
      "eval_token_accuracy": 0.8785794346978557,
      "failure_reason": "",
      "ffn_dim": 256,
      "final_train_loss": 0.24009886384010315,
      "git_commit": "525791fb5f020146bbd8aee3400c3ac7fb998521",
      "gpu_name": "NVIDIA A100-SXM4-80GB",
      "graph_certified": "",
      "graph_id": "v06_B16_d8_s2_c41f9afbd3840ed1",
      "graph_seed": 2,
      "heads": 4,
      "host": "hhpc",
      "implementation_certified": false,
      "lambda_G": 0.4430783779678246,
      "layers": 8,
      "learning_rate": 0.001,
      "local_or_remote": "remote",
      "log_every": 50,
      "log_path": "logs/copy_v06_main_n512_20260612_220241.log",
      "method": "random_regular",
      "metrics_path": "outputs/copy_v06_main_n512/train_N512_seed0_random_regular/metrics.jsonl",
      "mu_H": 0.5491481939947735,
      "multiplicity_mode": "unique_log_m",
      "neighbor_shape": [
        1040,
        64
      ],
      "num_values": 4,
      "optimizer": "adamw",
      "output_dir": "outputs/copy_v06_main_n512/train_N512_seed0_random_regular",
      "pad_token": 0,
      "peak_allocated_gb": 10.50410270690918,
      "peak_reserved_gb": 10.986328125,
      "pre_causal_pair_count": 81179,
      "pre_causal_unique_K_mean": 78.05673076923077,
      "raw_K": 80,
      "remote_local_overlap_mean": 0.0,
      "rho_bound": 0.860373989287474,
      "rho_exact": 0.5999831601197602,
      "run_id": "train_N512_seed0_random_regular",
      "seed": 0,
      "self_loop_rate": 1.0,
      "sep_token": 5,
      "status": "ok",
      "steps": 5000,
      "target_in_1hop_rate": 0.042884990253411304,
      "target_in_2hop_rate": 0.9512670565302144,
      "target_in_Lhop_rate": 0.9980506822612085,
      "task": "copy",
      "theory_aligned_method": false,
      "timestamp": "2026-06-12T14:57:15.782179+00:00",
      "tokens_per_sec": 37105.40941926362,
      "torch_version": "2.10.0+cu128",
      "training_curves_path": "outputs/copy_v06_main_n512/train_N512_seed0_random_regular/training_curves.png",
      "unique_K_mean": 40.087501525878906,
      "unreachable_rate": 0.001949317738791423,
      "version": "v06"
    },
    {
      "B": 16,
      "CUDA_VISIBLE_DEVICES": "3",
      "G_type": "permutation_regular",
      "H_type": "permutation_regular",
      "N_eval": 512,
      "N_train": 512,
      "T": 1040,
      "T_raw": 1026,
      "architecture": "transformer",
      "artifact_dir": "outputs/copy_v06_main_n512/train_N512_seed0_zigzag_boolean",
      "attention_backend": "split",
      "attention_pair_count_after_causal": 31033,
      "average_shortest_path": 2.733201581027668,
      "batch_size": 16,
      "block_pair_shape": null,
      "causal": true,
      "certified": false,
      "command": "/home/huiwei/miniconda3/envs/ysx_base/bin/python scripts/synthetic_mvp.py --config configs/copy_v06_main_n512.json --output-dir outputs/copy_v06_main_n512",
      "config_path": "configs/copy_v06_main_n512.json",
      "config_sha256": "7e9c686443ac544daa2a3333a1785c9568272415f90c77ab7a0dbbf59a77ed9b",
      "copy_mode": "full_copy",
      "d": 8,
      "d_model": 128,
      "data_mode": "online",
      "dropout": 0.1,
      "duplicate_rate": 0.6270072221755981,
      "effective_K_max_after_causal": 63,
      "effective_K_mean_after_causal": 29.83942222595215,
      "effective_K_min_after_causal": 1,
      "elapsed_sec": 1866.2317732032388,
      "eos_token": 6,
      "eval_batches": 50,
      "eval_eos_accuracy": 1.0,
      "eval_every": 50,
      "eval_loss": 0.6918463325500488,
      "eval_sequence_accuracy": 0.0,
      "eval_token_accuracy": 0.6280433723196881,
      "failure_reason": "",
      "ffn_dim": 256,
      "final_train_loss": 0.6976962089538574,
      "git_commit": "525791fb5f020146bbd8aee3400c3ac7fb998521",
      "gpu_name": "NVIDIA A100-SXM4-80GB",
      "graph_certified": true,
      "graph_id": "v06_B16_d8_s2_c41f9afbd3840ed1",
      "graph_seed": 2,
      "heads": 4,
      "host": "hhpc",
      "implementation_certified": false,
      "lambda_G": 0.4430783779678246,
      "layers": 8,
      "learning_rate": 0.001,
      "local_or_remote": "remote",
      "log_every": 50,
      "log_path": "logs/copy_v06_main_n512_20260612_220241.log",
      "method": "zigzag_boolean",
      "metrics_path": "outputs/copy_v06_main_n512/train_N512_seed0_zigzag_boolean/metrics.jsonl",
      "mu_H": 0.5491481939947735,
      "multiplicity_mode": "unique_log_m",
      "neighbor_shape": [
        1040,
        53
      ],
      "num_values": 4,
      "optimizer": "adamw",
      "output_dir": "outputs/copy_v06_main_n512/train_N512_seed0_zigzag_boolean",
      "pad_token": 0,
      "peak_allocated_gb": 8.886736392974854,
      "peak_reserved_gb": 9.1640625,
      "pre_causal_pair_count": 61230,
      "pre_causal_unique_K_mean": 58.875,
      "raw_K": 80,
      "remote_local_overlap_mean": 0.0,
      "rho_bound": 0.860373989287474,
      "rho_exact": 0.5999831601197602,
      "run_id": "train_N512_seed0_zigzag_boolean",
      "seed": 0,
      "self_loop_rate": 1.0,
      "sep_token": 5,
      "status": "ok",
      "steps": 5000,
      "target_in_1hop_rate": 0.04483430799220273,
      "target_in_2hop_rate": 0.39571150097465885,
      "target_in_Lhop_rate": 0.98635477582846,
      "task": "copy",
      "theory_aligned_method": false,
      "timestamp": "2026-06-12T16:01:02.517166+00:00",
      "tokens_per_sec": 44581.815182148464,
      "torch_version": "2.10.0+cu128",
      "training_curves_path": "outputs/copy_v06_main_n512/train_N512_seed0_zigzag_boolean/training_curves.png",
      "unique_K_mean": 29.83942222595215,
      "unreachable_rate": 0.01364522417153996,
      "version": "v06"
    },
    {
      "B": 16,
      "CUDA_VISIBLE_DEVICES": "3",
      "G_type": "permutation_regular",
      "H_type": "permutation_regular",
      "N_eval": 512,
      "N_train": 512,
      "T": 1040,
      "T_raw": 1026,
      "architecture": "transformer",
      "artifact_dir": "outputs/copy_v06_main_n512/train_N512_seed0_zigzag_certified",
      "attention_backend": "split",
      "attention_pair_count_after_causal": 31033,
      "average_shortest_path": 2.733201581027668,
      "batch_size": 16,
      "block_pair_shape": null,
      "causal": true,
      "certified": true,
      "command": "/home/huiwei/miniconda3/envs/ysx_base/bin/python scripts/synthetic_mvp.py --config configs/copy_v06_main_n512.json --output-dir outputs/copy_v06_main_n512",
      "config_path": "configs/copy_v06_main_n512.json",
      "config_sha256": "7e9c686443ac544daa2a3333a1785c9568272415f90c77ab7a0dbbf59a77ed9b",
      "copy_mode": "full_copy",
      "d": 8,
      "d_model": 128,
      "data_mode": "online",
      "dropout": 0.1,
      "duplicate_rate": 0.6270072221755981,
      "effective_K_max_after_causal": 63,
      "effective_K_mean_after_causal": 29.83942222595215,
      "effective_K_min_after_causal": 1,
      "elapsed_sec": 1949.7408073116094,
      "eos_token": 6,
      "eval_batches": 50,
      "eval_eos_accuracy": 1.0,
      "eval_every": 50,
      "eval_loss": 0.6976403307914734,
      "eval_sequence_accuracy": 0.0,
      "eval_token_accuracy": 0.6248513645224172,
      "failure_reason": "",
      "ffn_dim": 256,
      "final_train_loss": 0.7057569622993469,
      "git_commit": "525791fb5f020146bbd8aee3400c3ac7fb998521",
      "gpu_name": "NVIDIA A100-SXM4-80GB",
      "graph_certified": true,
      "graph_id": "v06_B16_d8_s2_c41f9afbd3840ed1",
      "graph_seed": 2,
      "heads": 4,
      "host": "hhpc",
      "implementation_certified": true,
      "lambda_G": 0.4430783779678246,
      "layers": 8,
      "learning_rate": 0.001,
      "local_or_remote": "remote",
      "log_every": 50,
      "log_path": "logs/copy_v06_main_n512_20260612_220241.log",
      "method": "zigzag_certified",
      "metrics_path": "outputs/copy_v06_main_n512/train_N512_seed0_zigzag_certified/metrics.jsonl",
      "mu_H": 0.5491481939947735,
      "multiplicity_mode": "unique_log_m",
      "neighbor_shape": [
        1040,
        53
      ],
      "num_values": 4,
      "optimizer": "adamw",
      "output_dir": "outputs/copy_v06_main_n512/train_N512_seed0_zigzag_certified",
      "pad_token": 0,
      "peak_allocated_gb": 8.886380195617676,
      "peak_reserved_gb": 9.1640625,
      "pre_causal_pair_count": 61230,
      "pre_causal_unique_K_mean": 58.875,
      "raw_K": 80,
      "remote_local_overlap_mean": 0.0,
      "rho_bound": 0.860373989287474,
      "rho_exact": 0.5999831601197602,
      "run_id": "train_N512_seed0_zigzag_certified",
      "seed": 0,
      "self_loop_rate": 1.0,
      "sep_token": 5,
      "status": "ok",
      "steps": 5000,
      "target_in_1hop_rate": 0.04483430799220273,
      "target_in_2hop_rate": 0.39571150097465885,
      "target_in_Lhop_rate": 0.98635477582846,
      "task": "copy",
      "theory_aligned_method": true,
      "timestamp": "2026-06-12T15:29:50.955522+00:00",
      "tokens_per_sec": 42672.33864521711,
      "torch_version": "2.10.0+cu128",
      "training_curves_path": "outputs/copy_v06_main_n512/train_N512_seed0_zigzag_certified/training_curves.png",
      "unique_K_mean": 29.83942222595215,
      "unreachable_rate": 0.01364522417153996,
      "version": "v06"
    }
  ],
  "status": "ok"
}
